MANIFEST.in
README.md
requirements.txt
setup.cfg
setup.py
napalm_fortios/__init__.py
napalm_fortios/fortios.py
napalm_fortios.egg-info/PKG-INFO
napalm_fortios.egg-info/SOURCES.txt
napalm_fortios.egg-info/dependency_links.txt
napalm_fortios.egg-info/requires.txt
napalm_fortios.egg-info/top_level.txt