Metadata-Version: 1.1
Name: napalm-fortios
Version: 0.4.1
Summary: Network Automation and Programmability Abstraction Layer with Multivendor support
Home-page: https://github.com/napalm-automation/napalm-fortios
Author: David Barroso
Author-email: dbarrosop@dravetech.com
License: UNKNOWN
Platform: UNKNOWN
Classifier: Topic :: Utilities
Classifier: Programming Language :: Python
Classifier: Operating System :: POSIX :: Linux
Classifier: Operating System :: MacOS
